co2_switzerland/ const.py
co2_switzerland/__init__.py
co2_switzerland/cli/cli.py
co2_switzerland-0.1.0.dist-info/METADATA
co2_switzerland-0.1.0.dist-info/WHEEL
co2_switzerland-0.1.0.dist-info/RECORD
